necrypt/__init__.py
necrypt/_version.py
necrypt/necrypt.py
necrypt-0.0.4.dist-info/LICENSE
necrypt-0.0.4.dist-info/METADATA
necrypt-0.0.4.dist-info/WHEEL
necrypt-0.0.4.dist-info/top_level.txt
necrypt-0.0.4.dist-info/RECORD
