Metadata-Version: 2.1
Name: necrypt
Version: 0.0.4
Summary: Encryption method
Home-page: https://github.com/mghorbani2357/Necrypt
Author: Mohsen Ghorbani
Author-email: m.ghorbani2357@gmail.com
License: MIT
Platform: UNKNOWN
Classifier: Intended Audience :: Developers
Classifier: License :: OSI Approved :: MIT License
Classifier: Operating System :: MacOS
Classifier: Operating System :: POSIX :: Linux
Classifier: Operating System :: OS Independent
Classifier: Topic :: Software Development :: Libraries :: Python Modules
Classifier: Programming Language :: Python :: Implementation :: PyPy
Requires-Dist: pycryptodome (~=3.9.9)
